Workbook

Sheet Summary
B2: AtliQ Contract Risk Analyzer — Cost Estimation & Savings (production AI product)
B3: Monthly figures unless stated. Change the blue / yellow inputs on each sheet — every total recalculates.
B5: Legend
B6: Blue text | C6: Input / assumption you can change
B7: Black text | C7: Formula (do not overwrite)
B8: Green text | C8: Linked from another sheet
B9: Yellow fill | C9: Key assumption to validate with leadership
B11: AI running cost | E11: Savings & ROI
B12: Component | C12: Cost | E12: Component | F12: Value
B13: Selected model | C13: =Inference!F14 | E13: Manual review cost per month | F13: ='Cost Savings'!E23
B14: Reviews per month | C14: =Inference!C16 | E14: Cost with AI per month (people + AI) | F14: ='Cost Savings'!E38
B15: Inference cost per review | C15: =Inference!F15 | E15: Savings per month | F15: ='Cost Savings'!E41
B16: Inference per month | C16: =Inference!F16 | E16: % Savings | F16: ='Cost Savings'!E42
B17: Embeddings per month | C17: =Embeddings!D30 | E17: Savings per year | F17: =F15*12
B18: Infrastructure per month | C18: =Infrastructure!C20 | E18: CEO hours freed per month | F18: ='Cost Savings'!E43
B19: Total AI running cost per month | C19: =C16+C17+C18 | E19: Risk & revenue protected per year | F19: ='Cost Savings'!H13
B20: Total AI running cost per year | C20: =C19*12 | E20: Payback period (months) | F20: =IF(F15<=0,"n/a",C28/F15)
E21: First-year net benefit (savings only) | F21: =F17-C28
B22: One-time setup | E22: First-year net benefit (incl. risk avoided) | F22: =F17+F19-C28
B23: Component | C23: Cost | E23: AI running cost as % of manual cost | F23: =IF(F13=0,0,C19/F13)
B24: Indexing historical contracts & notes | C24: =Embeddings!D31
B25: Build & rollout effort (hours) | C25: 240
B26: Blended engineering cost per hour | C26: 40 | E26: Scale check — AI cost if volume grows
B27: Human verification of commitments register (hours) | C27: 16 | E27: Contracts per month | F27: AI running cost per month
B28: Total one-time cost | C28: =C24+C25*C26+C27*'Cost Savings'!E18 | E28: 9 | F28: =(Inference!$F$16+Embeddings!$D$30)/Inference!$C$14*E28+Infrastructure!$C$20
E29: 25 | F29: =(Inference!$F$16+Embeddings!$D$30)/Inference!$C$14*E29+Infrastructure!$C$20
E30: 50 | F30: =(Inference!$F$16+Embeddings!$D$30)/Inference!$C$14*E30+Infrastructure!$C$20
E31: 100 | F31: =(Inference!$F$16+Embeddings!$D$30)/Inference!$C$14*E31+Infrastructure!$C$20

Sheet Inference
B2: Inference — LLM cost per contract review (AtliQ Contract Risk Analyzer, production)
B4: Base Calculation (per contract review) | E4: Model Selection + Cost Estimation
B5: Description | C5: Quantity (tokens) | E5: Model Name | F5: Input cost($) per 1M token | G5: Output cost($) per 1M token | H5: Cost per input review($) | I5: Cost per output review($) | J5: Total cost per review | K5: Review cost per month | L5: Extraction cost per month | M5: Total inference cost per month | N5: Pricing source
B6: System prompt + guardrails | C6: 1200 | E6: GPT-6 Astra | F6: 10 | G6: 50 | H6: =F6*$C$11/1000000 | I6: =G6*$C$12/1000000 | J6: =H6+I6 | K6: =J6*$C$16 | L6: =(F6*$C$21+G6*$C$22)/1000000*$C$24 | M6: =K6+L6 | N6: pricepertoken.com (Sep 2026)
B7: Review setup + deal context note | C7: 300 | E7: GPT-5.6 Sol | F7: 4 | G7: 20 | H7: =F7*$C$11/1000000 | I7: =G7*$C$12/1000000 | J7: =H7+I7 | K7: =J7*$C$16 | L7: =(F7*$C$21+G7*$C$22)/1000000*$C$24 | M7: =K7+L7 | N7: pricepertoken.com (Sep 2026) — promotional to 21 Nov 2026
B8: Incoming contract text | C8: =C20*Embeddings!$D$3 | E8: GPT-5.6 Terra | F8: 2 | G8: 12 | H8: =F8*$C$11/1000000 | I8: =G8*$C$12/1000000 | J8: =H8+I8 | K8: =J8*$C$16 | L8: =(F8*$C$21+G8*$C$22)/1000000*$C$24 | M8: =K8+L8 | N8: pricepertoken.com (Sep 2026)
B9: Retrieved commitments & precedents (RAG) | C9: =8*400 | E9: Claude Opus | F9: 5 | G9: 25 | H9: =F9*$C$11/1000000 | I9: =G9*$C$12/1000000 | J9: =H9+I9 | K9: =J9*$C$16 | L9: =(F9*$C$21+G9*$C$22)/1000000*$C$24 | M9: =K9+L9 | N9: finout.io / morphllm.com (2026)
B10: Rule-engine findings + contract outline | C10: 1200 | E10: Claude Sonnet | F10: 3 | G10: 15 | H10: =F10*$C$11/1000000 | I10: =G10*$C$12/1000000 | J10: =H10+I10 | K10: =J10*$C$16 | L10: =(F10*$C$21+G10*$C$22)/1000000*$C$24 | M10: =K10+L10 | N10: finout.io / morphllm.com (2026)
B11: Total input tokens per review | C11: =SUM(C6:C10) | E11: Claude Haiku | F11: 1 | G11: 5 | H11: =F11*$C$11/1000000 | I11: =G11*$C$12/1000000 | J11: =H11+I11 | K11: =J11*$C$16 | L11: =(F11*$C$21+G11*$C$22)/1000000*$C$24 | M11: =K11+L11 | N11: finout.io / morphllm.com (2026)
B12: Total output tokens per review | C12: 4000 | E12: Groq gpt-oss-120b | F12: 0.15 | G12: 0.6 | H12: =F12*$C$11/1000000 | I12: =G12*$C$12/1000000 | J12: =H12+I12 | K12: =J12*$C$16 | L12: =(F12*$C$21+G12*$C$22)/1000000*$C$24 | M12: =K12+L12 | N12: flexprice.io / computeprices.com (Aug 2026) — used in prototype
B13: Total tokens per review | C13: =C11+C12
B14: Contracts received per month | C14: 9 | E14: Selected model for production | F14: Claude Sonnet
B15: Review runs per contract (incl. re-reviews) | C15: 2 | E15: Selected model — cost per review | F15: =INDEX($J$6:$J$12,MATCH($F$14,$E$6:$E$12,0))
B16: Total monthly reviews | C16: =C14*C15 | E16: Selected model — inference cost per month | F16: =INDEX($M$6:$M$12,MATCH($F$14,$E$6:$E$12,0))
E17: Selected model — inference cost per year | F17: =F16*12
B18: Commitment extraction (when a contract is signed)
B19: Description | C19: Quantity
B20: Average words per contract | C20: 6000
B21: Extraction input tokens | C21: =800+C20*Embeddings!$D$3
B22: Extraction output tokens | C22: 1500
B23: Share of contracts that get signed | C23: 0.7
B24: Contracts signed per month | C24: =C14*C23

Sheet Embeddings
B1: Embeddings — indexing AtliQ's contract memory for retrieval (RAG)
C3: Token/word | D3: 1.3
C5: Signed contracts & annexures | F5: Emails & negotiation notes | I5: Meeting notes & tracker
C6: Component | D6: Quantity | F6: Component | G6: Quantity | I6: Component | J6: Quantity
C7: Number of signed documents | D7: 150 | F7: Number of emails / notes | G7: 3000 | I7: Number of notes / entries | J7: 300
C8: Number of words per document | D8: 6000 | F8: Number of words per item | G8: 250 | I8: Number of words per item | J8: 500
C9: Total number of words | D9: =D7*D8 | F9: Total number of words | G9: =G7*G8 | I9: Total number of words | J9: =J7*J8
C10: Total tokens | D10: =D9*$D$3 | F10: Total tokens | G10: =G9*$D$3 | I10: Total tokens | J10: =J9*$D$3
C13: RAG Embeddings — one-time indexing | F13: Monthly new documents
C14: Component | D14: Cost/Quantity | F14: Component | G14: Cost/Quantity
C15: Total tokens for RAG corpus | D15: =D10+G10+J10 | F15: Contract versions embedded per month | G15: =Inference!C16
C16: Cost per 1M token | D16: 0.13 | F16: Words per contract | G16: =Inference!C20
C17: Total one-time cost for RAG indexing | D17: =D15*D16/1000000 | F17: New emails / notes per month | G17: 200
F18: Words per email / note | G18: 250
F19: New tokens per month | G19: =(G15*G16+G17*G18)*$D$3
C20: Retrieval Query Embeddings | F20: Cost per 1M token | G20: =$D$16
C21: Component | D21: Cost/Quantity | F21: Total cost for new documents | G21: =G19*G20/1000000
C22: Retrieval queries per review | D22: 12
C23: Tokens per retrieval query | D23: 60
C24: Reviews per month | D24: =Inference!C16
C25: Total tokens per month | D25: =D22*D23*D24
C26: Cost per 1M token | D26: =$D$16
C27: Total cost for query embeddings | D27: =D25*D26/1000000
C30: Total cost of Embeddings per month | D30: =G21+D27
C31: One-time indexing cost (RAG corpus) | D31: =D17

Sheet Infrastructure
B1: Infrastructure — monthly hosting and services (production)
B3: Document processing (scanned PDFs)
B4: Component | C4: Quantity | D4: Note
B5: Contract versions per month | C5: =Inference!C16
B6: Average pages per contract | C6: 15
B7: Share of scanned documents needing OCR | C7: 0.2
B8: OCR price per 1,000 pages | C8: 1.5
B9: OCR cost per month | C9: =C5*C6*C7*C8/1000 | D9: Scanned pages × price
B12: Monthly infrastructure cost
B13: Component | C13: Cost per month | D13: Source / note
B14: Web app hosting (Vercel Pro, 1 seat) | C14: 20 | D14: Vercel Pro $20/seat/month incl. $20 usage credit (makerkit.dev, 2026). Hobby (free) does not allow commercial use.
B15: Database + vector store (Supabase Pro, pgvector) | C15: 25 | D15: Supabase Pro $25/month incl. $10 compute credit (focusreactive.com / supabase.com, 2026).
B16: Document OCR | C16: =C9 | D16: From the document-processing block above.
B17: File storage & backups | C17: 5 | D17: Contract files and generated reports (estimate).
B18: Monitoring, logging & error alerts | C18: 0 | D18: Free tiers sufficient at this volume (estimate).
B19: Sign-in / SSO (company identity provider) | C19: 0 | D19: Uses AtliQ's existing Google Workspace / Microsoft 365 (assumption).
B20: Total infrastructure cost per month | C20: =SUM(C14:C19)

Sheet Cost Savings
C1: Cost Savings — manual contract review vs. AI Contract Risk Analyzer (per month)
D3: Calculating manual review effort (today) | G3: Risk avoided (not included in % savings above)
D4: Component | E4: Quantity | G4: Component | H4: Cost
D5: Complex contracts per month (MSAs, partnerships, BAAs) | E5: 4 | G5: Brightwater-type incident: settlement | H5: 9000
D6: CEO hours per complex review | E6: 7 | G6: Brightwater-type incident: counsel fees | H6: 14200
D7: Standard contracts per month (NDAs, SOWs) | E7: 5 | G7: Brightwater-type incident: senior time lost | H7: =80*E19
D8: CEO hours per standard review | E8: 2 | G8: Cost of one incident | H8: =SUM(H5:H7)
D9: Re-review cycles per month (negotiated versions) | E9: =Inference!C14*(Inference!C15-1) | G9: Incidents avoided per year | H9: 1
D10: CEO hours per re-review | E10: 1.5 | G10: Deal lost to review-queue delay (SOW value) | H10: 55000
D11: Total CEO review hours per month | E11: =E5*E6+E7*E8+E9*E10 | G11: Gross margin on lost deals | H11: 0.35
D12: Stakeholder hours per contract (finding past contracts, emails) | E12: 2 | G12: Deals saved per year by faster turnaround | H12: 1
D13: Total stakeholder hours per month | E13: =E12*(E5+E7) | G13: Risk & revenue protected per year | H13: =H8*H9+H10*H11*H12
G14: Risk & revenue protected per month | H14: =H13/12
D16: Total monthly cost of manual review
D17: Component | E17: Cost
D18: CEO cost per hour (opportunity cost) | E18: 150
D19: Stakeholder cost per hour | E19: 35
D20: Outside counsel spend per month | E20: 1500
D21: CEO review cost per month | E21: =E11*E18
D22: Stakeholder cost per month | E22: =E13*E19
D23: Total cost of manual review per month | E23: =E20+E21+E22
D26: Cost with AI Contract Risk Analyzer
D27: Component | E27: Cost
D28: Reduction in CEO review effort | E28: 0.5
D29: Reduction in stakeholder search time | E29: 0.75
D30: Reduction in outside counsel spend | E30: 0.3
D31: Remaining CEO review cost | E31: =E21*(1-E28)
D32: Remaining stakeholder cost | E32: =E22*(1-E29)
D33: Remaining outside counsel spend | E33: =E20*(1-E30)
D34: Inference cost (selected model) | E34: =Inference!F16
D35: Embeddings cost | E35: =Embeddings!D30
D36: Infrastructure cost | E36: =Infrastructure!C20
D37: Total AI running cost per month | E37: =E34+E35+E36
D38: Total cost with AI Contract Risk Analyzer per month | E38: =E31+E32+E33+E37
D41: Total Savings (per month) | E41: =E23-E38
D42: % Savings | E42: =IF(E23=0,0,E41/E23)
D43: CEO hours freed per month | E43: =E11*E28

Sheet Assumptions & Sources
B1: Assumptions & sources
B3: Area | C3: Assumption | D3: Value / where | E3: Source
B4: Volume | C4: Contracts received per month | D4: Inference!C14 | E4: Dataset: 22 Sep 2026 contract-queue meeting (~9/month in 2026, ~5 in 2025)
B5: Volume | C5: Re-reviews: every negotiated version reviewed in full | D5: Inference!C15 | E5: MVP assumptions (#9), client meeting 2
B6: Baseline effort | C6: ~2 h standard review, 6–8 h complex; 3–4 contracts + 4–5 NDAs per month | D6: Cost Savings!E5:E8 | E6: MVP assumptions (#11), client meeting 2
B7: Target | C7: 50% reduction in median human review effort | D7: Cost Savings!E28 | E7: PRD §12 Success Metrics — North Star
B8: Value of time | C8: CEO opportunity cost $150/h; stakeholder $35/h | D8: Cost Savings!E18:E19 | E8: Assumption — validate with leadership
B9: Counsel | C9: CareBridge BAA review $3,800; Gulf Crown review ₹1,20,000 | D9: Cost Savings!E20 | E9: Dataset: negotiation notes, 25 Sep 2026 counsel call
B10: Risk | C10: Brightwater: $9,000 settlement + $14,200 counsel + ~2 weeks senior time | D10: Cost Savings!H5:H7 | E10: Dataset: 14 Apr 2026 post-mortem
B11: Risk | C11: ShopSwift $55k SOW lost to a 9-day review delay | D11: Cost Savings!H10 | E11: Dataset: contract tracker C-019, 22 Sep 2026 meeting
B12: Tokens | C12: ~1.3 tokens per English word | D12: Embeddings!D3 | E12: Industry rule of thumb (same as reference model)
B13: Pricing | C13: GPT-6 Astra $10/$50; GPT-5.6 Sol $4/$20 (promo); GPT-5.6 Terra $2/$12 per 1M tokens | D13: Inference!F6:G8 | E13: https://pricepertoken.com (Sep 2026) — verify https://developers.openai.com/api/docs/pricing
B14: Pricing | C14: Claude Opus $5/$25; Sonnet $3/$15; Haiku $1/$5 per 1M tokens | D14: Inference!F9:G11 | E14: https://finout.io/blog/anthropic-api-pricing ; https://www.morphllm.com/anthropic-claude-api-pricing — verify on Anthropic pricing page
... B20: Scope | C20: Excludes AtliQ staff time to build/maintain the product (see Summary one-time build cost) | D20: Summary | E20: Assumption
